{
    "Rank": 960,
    "Study": {
        "ProtocolSection": {
            "IdentificationModule": {
                "NCTId": "NCT00961610",
                "OrgStudyIdInfo": {
                    "OrgStudyId": "PP-07024"
                },
                "Organization": {
                    "OrgFullName": "Danish Cancer Society",
                    "OrgClass": "OTHER"
                },
                "BriefTitle": "Internet-based Support in Cancer Rehabilitation",
                "OfficialTitle": "Internet-based Support in the Rehabilitation of Danish Cancer Survivors"
            },
            "StatusModule": {
                "StatusVerifiedDate": "August 2009",
                "OverallStatus": "Completed",
                "ExpandedAccessInfo": {
                    "HasExpandedAccess": "No"
                },
                "StartDateStruct": {
                    "StartDate": "April 2004"
                },
                "PrimaryCompletionDateStruct": {
                    "PrimaryCompletionDate": "December 2006",
                    "PrimaryCompletionDateType": "Actual"
                },
                "CompletionDateStruct": {
                    "CompletionDate": "December 2006",
                    "CompletionDateType": "Actual"
                },
                "StudyFirstSubmitDate": "August 17, 2009",
                "StudyFirstSubmitQCDate": "August 18, 2009",
                "StudyFirstPostDateStruct": {
                    "StudyFirstPostDate": "August 19, 2009",
                    "StudyFirstPostDateType": "Estimate"
                },
                "LastUpdateSubmitDate": "August 18, 2009",
                "LastUpdatePostDateStruct": {
                    "LastUpdatePostDate": "August 19, 2009",
                    "LastUpdatePostDateType": "Estimate"
                }
            },
            "SponsorCollaboratorsModule": {
                "ResponsibleParty": {
                    "ResponsiblePartyOldNameTitle": "Christoffer Johansen",
                    "ResponsiblePartyOldOrganization": "Department of Psychosocial Cancer Research"
                },
                "LeadSponsor": {
                    "LeadSponsorName": "Danish Cancer Society",
                    "LeadSponsorClass": "OTHER"
                },
                "CollaboratorList": {
                    "Collaborator": [
                        {
                            "CollaboratorName": "TrygFonden, Denmark",
                            "CollaboratorClass": "INDUSTRY"
                        },
                        {
                            "CollaboratorName": "IMK Almene Fond",
                            "CollaboratorClass": "OTHER"
                        }
                    ]
                }
            },
            "OversightModule": {
                "OversightHasDMC": "Yes"
            },
            "DescriptionModule": {
                "BriefSummary": "This 2-arm randomized trial assessed the incremental effect of providing a lecture on Internet use followed by participation in an Internet-based peer support group following a week-long rehabilitation program, over and above any possible general effect of participation in the rehabilitation program.\n\nPrimary outcome measures are adjustment to cancer and mood disturbance."
            },
            "ConditionsModule": {
                "ConditionList": {
                    "Condition": [
                        "Cancer"
                    ]
                },
                "KeywordList": {
                    "Keyword": [
                        "internet support",
                        "cancer",
                        "rehabilitation"
                    ]
                }
            },
            "DesignModule": {
                "StudyType": "Observational",
                "DesignInfo": {
                    "DesignObservationalModelList": {
                        "DesignObservationalModel": [
                            "Case-Control"
                        ]
                    },
                    "DesignTimePerspectiveList": {
                        "DesignTimePerspective": [
                            "Prospective"
                        ]
                    }
                },
                "EnrollmentInfo": {
                    "EnrollmentCount": "794",
                    "EnrollmentType": "Actual"
                }
            },
            "ArmsInterventionsModule": {
                "ArmGroupList": {
                    "ArmGroup": [
                        {
                            "ArmGroupLabel": "Internet support group Intervention",
                            "ArmGroupInterventionList": {
                                "ArmGroupInterventionName": [
                                    "Behavioral: Internet peer-support group"
                                ]
                            }
                        },
                        {
                            "ArmGroupLabel": "Control group",
                            "ArmGroupInterventionList": {
                                "ArmGroupInterventionName": [
                                    "Behavioral: Internet peer-support group"
                                ]
                            }
                        }
                    ]
                },
                "InterventionList": {
                    "Intervention": [
                        {
                            "InterventionType": "Behavioral",
                            "InterventionName": "Internet peer-support group",
                            "InterventionDescription": "The Internet peer-support groups provided a self-guided space for communication, including an Internet discussion forum, a live chat room and a personal message system. No therapeutic content or information services were offered within the groups.\n\nAll Internet groups were run in a browser-based software platform with access through the website of the Danish Cancer Society (http://www.cancer.dk). All discussions were protected by a password and communication was encrypted.\n\nThe Internet groups in this study were all closed peer-support groups, accessible only by an invitation received by e-mail after registration for the study. The groups were open to access 24 h a day for 13 months from their individual starting date.",
                            "InterventionArmGroupLabelList": {
                                "InterventionArmGroupLabel": [
                                    "Control group",
                                    "Internet support group Intervention"
                                ]
                            }
                        }
                    ]
                }
            },
            "OutcomesModule": {
                "PrimaryOutcomeList": {
                    "PrimaryOutcome": [
                        {
                            "PrimaryOutcomeMeasure": "Adjustment to cancer measured by the Mini-MAC scale Mood disturbance measured by POMS-SF scale"
                        }
                    ]
                },
                "SecondaryOutcomeList": {
                    "SecondaryOutcome": [
                        {
                            "SecondaryOutcomeMeasure": "Self-rated global health"
                        }
                    ]
                }
            },
            "EligibilityModule": {
                "EligibilityCriteria": "Inclusion Criteria:\n\nCancer survivors who were randomized for or self-selected to a rehabilitation course at the Dallund Rehabilitation Centre were included in the study.\n\nExclusion Criteria:\n\nRehabilitation course weeks in which cancer survivors over 50 years of age were targeted specifically were excluded.",
                "Gender": "All",
                "MinimumAge": "18 Years",
                "StdAgeList": {
                    "StdAge": [
                        "Adult",
                        "Older Adult"
                    ]
                },
                "StudyPopulation": "A total of 66 scheduled rehabilitation course weeks were screened for eligibility between 19 April 2004 and 31 December 2005 from the Rehabilitation Centre Dallund in Denmark. All 58 eligible courses including 921 individuals were enrolled and randomized as 27 case weeks (n = 416 persons) and 31 control weeks (n = 505 persons). Baseline assessments were obtained from 799 individuals. Data from 10 individuals (5 from each treatment group) were subsequently excluded, as they did not attend a rehabilitation course week as planned, leaving final study population of 794 individuals analyzed by 'intention-to-treat' (case: n = 361/794; control: n = 433/794). Participants were followed up for 12 months in accordance with their dates of attendance of the rehabilitation course from 19 April 2004 till 31 December 2006.",
                "SamplingMethod": "Probability Sample"
            },
            "ContactsLocationsModule": {
                "OverallOfficialList": {
                    "OverallOfficial": [
                        {
                            "OverallOfficialName": "Christoffer Johansen, MD, PhD, DrMedSci",
                            "OverallOfficialAffiliation": "Department of Psychosocial Cancer Research",
                            "OverallOfficialRole": "Principal Investigator"
                        }
                    ]
                },
                "LocationList": {
                    "Location": [
                        {
                            "LocationFacility": "Department of Psychsocial Cancer Research",
                            "LocationCity": "Copenhagen",
                            "LocationZip": "2100",
                            "LocationCountry": "Denmark"
                        }
                    ]
                }
            }
        },
        "DerivedSection": {
            "MiscInfoModule": {
                "VersionHolder": "September 08, 2023"
            }
        }
    }
}